SSUphysicsTools/Plots.py
SSUphysicsTools/__init__.py
SSUphysicsTools/data_analysis.py
SSUphysicsTools/data_processing.py
SSUphysicsTools/exceptions.py
SSUphysicsTools/getting_data.py
tests/__init__.py
tests/test_init.py
SSUphysicsTools-2.1.3.dist-info/METADATA
SSUphysicsTools-2.1.3.dist-info/WHEEL
SSUphysicsTools-2.1.3.dist-info/top_level.txt
SSUphysicsTools-2.1.3.dist-info/RECORD
