Metadata-Version: 2.1
Name: SSUphysicsTools
Version: 2.1.3
Summary: 숭실대학교 물리학과 실험에 사용되는 데이터 처리 및 시각화 도구
Home-page: https://github.com/kty1004/SSUphysicsExperiment_Supporting_tools?tab=readme-ov-file#readme
Author: Taeyoung Kim
Author-email: rocketman@soongsil.ac.kr
Classifier: Programming Language :: Python :: 3
Classifier: License :: OSI Approved :: MIT License
Classifier: Operating System :: OS Independent
Requires-Python: >=3.13.0
Requires-Dist: numpy
Requires-Dist: scipy
Requires-Dist: matplotlib
Requires-Dist: pandas
